[
  {
    "id": 1,
    "name": "name1",
    "text": "texsadxttexttext",
    "photo": "ph.png"
  },
  {
    "id": 2,
    "name": "name2",
    "text": "texttexttexttexttexttexttexttexttexttextdsadastext",
    "photo": "ph.png"
  },
  {
    "id": 3,
    "name": "name3",
    "text": "texttexttexttextteasdxttexttexttexttext",
    "photo": "ph.png"
  },
  {
    "id": 4,
    "name": "name4",
    "text": "texttexttexttextext",
    "photo": "ph.png"
  },
  {
    "id": 5,
    "name": "name5",
    "text": "texttexttexttexttexttexttexttexttext",
    "photo": "ph.png"
  },
  {
    "id": 6,
    "name": "name6",
    "text": "texttexttexttexttexttexttexttexttexttexttexttexttexttexttexttext",
    "photo": "ph.png"
  },
  {
    "id": 7,
    "name": "name7",
    "text": "texttexttexttexttexttexttexttext",
    "photo": "ph.png"
  }
]
